cryptomailer/__init__.py
cryptomailer/crypt.py
cryptomailer/mailer_receive.py
cryptomailer/mailer_send.py
cryptomailer-0.0.2.dist-info/LICENSE
cryptomailer-0.0.2.dist-info/METADATA
cryptomailer-0.0.2.dist-info/WHEEL
cryptomailer-0.0.2.dist-info/top_level.txt
cryptomailer-0.0.2.dist-info/RECORD
