Metadata-Version: 2.1
Name: cryptomailer
Version: 0.0.2
Summary: A package to send and receive encrypted mails via Gmail.
Home-page: https://github.com/AdityaSingh17/CryptoMailer
Author: Aditya Rajneesh Singh
Author-email: adityarsingh17@gmail.com
License: UNKNOWN
Platform: UNKNOWN
Classifier: Programming Language :: Python :: 3
Classifier: License :: OSI Approved :: MIT License
Classifier: Operating System :: OS Independent
Requires-Python: >=3.6
